[{"ScenicSpotID":"C1_376560000A_000128","ScenicSpotName":"花嶼、花嶼燈塔","DescriptionDetail":"花嶼位在望安島西北方偏南，是澎湖縣最西方的島嶼，也是全台的極西，最高處約53公尺。 花嶼地形與澎湖其他島嶼相似，就地質卻是不同，其他島嶼以玄武岩為主，而構成花嶼的岩石主要為安山岩，是由九千萬年前到五千萬年前形成，為澎湖群島最古老的島嶼；在長期的風化作用下，刻劃出了不同的岩石景觀。 在退潮時，花嶼的東南側海蝕礁石上，可看到傳說中「仙腳石印」的左腳，與望安嶼天台山的右腳相呼應；島上還有夫妻石（情人石）、石觀音、石猴、老翁石...等岩石景觀。 為在花嶼山頂的花嶼燈塔，是花嶼附近的主要地標，日本人因軍事上具重要地位而興建，於民國28年（西元1939年）完工，塔身為鋼筋混凝土白色圓形燈塔，塔高12.5公尺，是台灣最西的燈塔；裝有四等電石氣閃光燈，每五秒閃白光一次，光力1600支燭光。 【建議停留時間】 4小時或過夜","Description":"花嶼燈塔素有「花嶼之光」的美譽，是花嶼的主要地標，為日本人因軍事目的而興建。其塔身為圓形鋼筋混凝土結構，漆成白色，塔高12.5公尺。由於花嶼位居澎湖群的最西端，約在東經119度5分，比台灣本島約晚20秒看到落日，是台灣地區最晚看到日落的燈塔。","Phone":"886-6-9216445","Address":"澎湖縣望安鄉花嶼的山頂上","ZipCode":"882","TravelInfo":"南海船班交通資訊（點此連結）","OpenTime":"Sun 24 hours；Mon 24 hours；Tue 24 hours；Wed 24 hours；Thu 24 hours；Fri 24 hours；Sat 24 hours","Picture":{"PictureUrl1":"https://penghutravel.com/FileDownload/TravelInformation/NotSet/Scenery/54/花嶼、花嶼燈塔01.jpg","PictureDescription1":"進碼頭前可見的花嶼夫妻石（情人石）","PictureUrl2":"https://penghutravel.com/FileDownload/TravelInformation/NotSet/Scenery/54/花嶼、花嶼燈塔03.jpg","PictureDescription2":"花嶼山頂的花嶼燈塔","PictureUrl3":"https://penghutravel.com/FileDownload/TravelInformation/NotSet/Scenery/54/花嶼燈塔.jpg","PictureDescription3":"花嶼燈塔"},"Position":{"PositionLon":119.3137435913086,"PositionLat":23.403629302978516,"GeoHash":"wshv5h985"},"Level":"非古蹟","ParkingPosition":{},"TicketInfo":"免費參觀","Remarks":"<ol>\t<li>請留意交通船班往返時間。</li>\t<li>島嶼資源有限，請遊客珍惜各項資源，並隨手將垃圾帶離島上，不增加島嶼負擔。</li></ol>","Keyword":"花嶼、花嶼燈塔","SrcUpdateTime":"2022-04-04T01:15:36+08:00","UpdateTime":"2022-04-04T01:34:30+08:00"}]